meddevstats/__init__.py
meddevstats/core/__init__.py
meddevstats/core/agreement.py
meddevstats/core/equivalence.py
meddevstats/core/performance.py
meddevstats/core/validation.py
meddevstats/utils/__init__.py
meddevstats/utils/reporters.py
meddevstats/utils/validators.py
meddevstats-0.1.0.dist-info/licenses/LICENSE
meddevstats-0.1.0.dist-info/METADATA
meddevstats-0.1.0.dist-info/WHEEL
meddevstats-0.1.0.dist-info/top_level.txt
meddevstats-0.1.0.dist-info/RECORD
